__init__.py
pymlgabj/__init__.py
pymlgabj/factory.py
pymlgabj/fitness.py
pymlgabj/strategy.py
jeremydimond_pymlga_blackjack-0.0.2.dist-info/METADATA
jeremydimond_pymlga_blackjack-0.0.2.dist-info/WHEEL
jeremydimond_pymlga_blackjack-0.0.2.dist-info/top_level.txt
jeremydimond_pymlga_blackjack-0.0.2.dist-info/RECORD
