Metadata-Version: 2.4
Name: jeremydimond.pymlga-blackjack
Version: 0.0.2
Summary: Python machine learning by genetic algorithm - blackjack strategy generator
Author-email: Jeremy Dimond <jeremy@jeremydimond.com>
Project-URL: Homepage, https://github.com/jeremydimond/pymlga-blackjack
Keywords: jeremydimond,ml,ai,genetic,algorithm,machine,learning,blackjack
Classifier: License :: OSI Approved :: MIT License
Classifier: Programming Language :: Python
Classifier: Programming Language :: Python :: 3
Requires-Python: >=3.9
Provides-Extra: dev
Requires-Dist: jeremydimond.pytesthelpers==1.0.4; extra == "dev"
Requires-Dist: jeremydimond.pymlga==0.6.0; extra == "dev"
Requires-Dist: jeremydimond.pygamesim==1.1.2; extra == "dev"
Requires-Dist: pytest<9.0.0; extra == "dev"
Requires-Dist: pytest-cov; extra == "dev"
Requires-Dist: pytest-tldr; extra == "dev"
Requires-Dist: bumpver; extra == "dev"
Requires-Dist: build; extra == "dev"
Requires-Dist: twine; extra == "dev"
